<s:Envelope xmlns:a="http://www.w3.org/2005/08/addressing" xmlns:s="http://schemas.xmlsoap.org/soap/envelope/">
  <s:Header>
    <a:Action s:mustUnderstand="1">http://tempuri.org/IBaseDataTypesRpcLit/RetDouble</a:Action>
    <a:MessageID>urn:uuid:4bb7c33a-314b-4300-bec3-7cdca834e40e</a:MessageID>
    <a:ReplyTo>
      <a:Address>http://www.w3.org/2005/08/addressing/anonymous</a:Address>
    </a:ReplyTo>
  </s:Header>
  <s:Body>
    <RetDouble xmlns="http://tempuri.org/">
      <inDouble xmlns="">-1</inDouble>
    </RetDouble>
  </s:Body>
</s:Envelope>