<s:Envelope xmlns:a="http://www.w3.org/2005/08/addressing" xmlns:s="http://schemas.xmlsoap.org/soap/envelope/">
  <s:Header>
    <a:Action s:mustUnderstand="1">http://tempuri.org/IBaseDataTypesDocLitW/RetDouble</a:Action>
    <a:MessageID>urn:uuid:40d53882-2eec-44e9-8651-f06afaf5bd48</a:MessageID>
    <a:ReplyTo>
      <a:Address>http://www.w3.org/2005/08/addressing/anonymous</a:Address>
    </a:ReplyTo>
  </s:Header>
  <s:Body>
    <RetDouble xmlns="http://tempuri.org/">
      <inDouble>-INF</inDouble>
    </RetDouble>
  </s:Body>
</s:Envelope>